prettytype/__init__.py
prettytype-0.1.0.dist-info/DESCRIPTION.rst
prettytype-0.1.0.dist-info/METADATA
prettytype-0.1.0.dist-info/RECORD
prettytype-0.1.0.dist-info/WHEEL
prettytype-0.1.0.dist-info/metadata.json
prettytype-0.1.0.dist-info/top_level.txt
