Metadata-Version: 2.0
Name: prettytype
Version: 0.1.0
Summary: Print types of nested structues
Home-page: https://github.com/stuglaser/prettytype
Author: Stu Glaser
Author-email: UNKNOWN
License: UNKNOWN
Platform: UNKNOWN
Classifier: Development Status :: 4 - Beta
Classifier: Intended Audience :: Developers
Classifier: License :: OSI Approved :: MIT License
Classifier: Programming Language :: Python :: 2
Classifier: Programming Language :: Python :: 2.7
